{
    "AAVE": [
        "AAVE/USDC:USDC"
    ],
    "ACE": [
        "ACE/USDC:USDC"
    ],
    "ADA": [
        "ADA/USDC:USDC"
    ],
    "AI": [
        "AI/USDC:USDC"
    ],
    "AI16Z": [
        "AI16Z/USDC:USDC"
    ],
    "AIXBT": [
        "AIXBT/USDC:USDC"
    ],
    "ALGO": [
        "ALGO/USDC:USDC"
    ],
    "ALT": [
        "ALT/USDC:USDC"
    ],
    "ANIME": [
        "ANIME/USDC:USDC"
    ],
    "APE": [
        "APE/USDC:USDC"
    ],
    "APT": [
        "APT/USDC:USDC"
    ],
    "AR": [
        "AR/USDC:USDC"
    ],
    "ARB": [
        "ARB/USDC:USDC"
    ],
    "ARK": [
        "ARK/USDC:USDC"
    ],
    "ATOM": [
        "ATOM/USDC:USDC"
    ],
    "AVAX": [
        "AVAX/USDC:USDC"
    ],
    "BABY": [
        "BABY/USDC:USDC"
    ],
    "BADGER": [
        "BADGER/USDC:USDC"
    ],
    "BANANA": [
        "BANANA/USDC:USDC"
    ],
    "BCH": [
        "BCH/USDC:USDC"
    ],
    "BERA": [
        "BERA/USDC:USDC"
    ],
    "BIGTIME": [
        "BIGTIME/USDC:USDC"
    ],
    "BIO": [
        "BIO/USDC:USDC"
    ],
    "BLAST": [
        "BLAST/USDC:USDC"
    ],
    "BLUR": [
        "BLUR/USDC:USDC"
    ],
    "BLZ": [
        "BLZ/USDC:USDC"
    ],
    "BNB": [
        "BNB/USDC:USDC"
    ],
    "BNT": [
        "BNT/USDC:USDC"
    ],
    "BOME": [
        "BOME/USDC:USDC"
    ],
    "BONK": [
        "KBONK/USDC:USDC"
    ],
    "BRETT": [
        "BRETT/USDC:USDC"
    ],
    "BSV": [
        "BSV/USDC:USDC"
    ],
    "BTC": [
        "BTC/USDC:USDC"
    ],
    "CAKE": [
        "CAKE/USDC:USDC"
    ],
    "CANTO": [
        "CANTO/USDC:USDC"
    ],
    "CATI": [
        "CATI/USDC:USDC"
    ],
    "CELO": [
        "CELO/USDC:USDC"
    ],
    "CFX": [
        "CFX/USDC:USDC"
    ],
    "CHILLGUY": [
        "CHILLGUY/USDC:USDC"
    ],
    "COMP": [
        "COMP/USDC:USDC"
    ],
    "CRV": [
        "CRV/USDC:USDC"
    ],
    "CYBER": [
        "CYBER/USDC:USDC"
    ],
    "DOGE": [
        "DOGE/USDC:USDC"
    ],
    "DOGS": [
        "KDOGS/USDC:USDC"
    ],
    "DOOD": [
        "DOOD/USDC:USDC"
    ],
    "DOT": [
        "DOT/USDC:USDC"
    ],
    "DYDX": [
        "DYDX/USDC:USDC"
    ],
    "DYM": [
        "DYM/USDC:USDC"
    ],
    "EIGEN": [
        "EIGEN/USDC:USDC"
    ],
    "ENA": [
        "ENA/USDC:USDC"
    ],
    "ENS": [
        "ENS/USDC:USDC"
    ],
    "ETC": [
        "ETC/USDC:USDC"
    ],
    "ETH": [
        "ETH/USDC:USDC"
    ],
    "ETHFI": [
        "ETHFI/USDC:USDC"
    ],
    "FARTCOIN": [
        "FARTCOIN/USDC:USDC"
    ],
    "FET": [
        "FET/USDC:USDC"
    ],
    "FIL": [
        "FIL/USDC:USDC"
    ],
    "FLOKI": [
        "KFLOKI/USDC:USDC"
    ],
    "FRIEND": [
        "FRIEND/USDC:USDC"
    ],
    "FTM": [
        "FTM/USDC:USDC"
    ],
    "FTT": [
        "FTT/USDC:USDC"
    ],
    "FXS": [
        "FXS/USDC:USDC"
    ],
    "GALA": [
        "GALA/USDC:USDC"
    ],
    "GAS": [
        "GAS/USDC:USDC"
    ],
    "GMT": [
        "GMT/USDC:USDC"
    ],
    "GMX": [
        "GMX/USDC:USDC"
    ],
    "GOAT": [
        "GOAT/USDC:USDC"
    ],
    "GRASS": [
        "GRASS/USDC:USDC"
    ],
    "GRIFFAIN": [
        "GRIFFAIN/USDC:USDC"
    ],
    "HBAR": [
        "HBAR/USDC:USDC"
    ],
    "HMSTR": [
        "HMSTR/USDC:USDC"
    ],
    "HPOS": [
        "HPOS/USDC:USDC"
    ],
    "HYPE": [
        "HYPE/USDC:USDC"
    ],
    "HYPER": [
        "HYPER/USDC:USDC"
    ],
    "ILV": [
        "ILV/USDC:USDC"
    ],
    "IMX": [
        "IMX/USDC:USDC"
    ],
    "INIT": [
        "INIT/USDC:USDC"
    ],
    "INJ": [
        "INJ/USDC:USDC"
    ],
    "IO": [
        "IO/USDC:USDC"
    ],
    "IOTA": [
        "IOTA/USDC:USDC"
    ],
    "IP": [
        "IP/USDC:USDC"
    ],
    "JELLY": [
        "JELLY/USDC:USDC"
    ],
    "JTO": [
        "JTO/USDC:USDC"
    ],
    "JUP": [
        "JUP/USDC:USDC"
    ],
    "KAITO": [
        "KAITO/USDC:USDC"
    ],
    "KAS": [
        "KAS/USDC:USDC"
    ],
    "KBONK": [
        "KBONK/USDC:USDC"
    ],
    "KDOGS": [
        "KDOGS/USDC:USDC"
    ],
    "KFLOKI": [
        "KFLOKI/USDC:USDC"
    ],
    "KLUNC": [
        "KLUNC/USDC:USDC"
    ],
    "KNEIRO": [
        "KNEIRO/USDC:USDC"
    ],
    "KPEPE": [
        "KPEPE/USDC:USDC"
    ],
    "KSHIB": [
        "KSHIB/USDC:USDC"
    ],
    "LAUNCHCOIN": [
        "LAUNCHCOIN/USDC:USDC"
    ],
    "LAYER": [
        "LAYER/USDC:USDC"
    ],
    "LDO": [
        "LDO/USDC:USDC"
    ],
    "LINEA": [
        "LINEA/USDC:USDC"
    ],
    "LINK": [
        "LINK/USDC:USDC"
    ],
    "LISTA": [
        "LISTA/USDC:USDC"
    ],
    "LOOM": [
        "LOOM/USDC:USDC"
    ],
    "LTC": [
        "LTC/USDC:USDC"
    ],
    "LUNC": [
        "KLUNC/USDC:USDC"
    ],
    "MANTA": [
        "MANTA/USDC:USDC"
    ],
    "MATIC": [
        "MATIC/USDC:USDC"
    ],
    "MAV": [
        "MAV/USDC:USDC"
    ],
    "MAVIA": [
        "MAVIA/USDC:USDC"
    ],
    "ME": [
        "ME/USDC:USDC"
    ],
    "MELANIA": [
        "MELANIA/USDC:USDC"
    ],
    "MEME": [
        "MEME/USDC:USDC"
    ],
    "MERL": [
        "MERL/USDC:USDC"
    ],
    "MEW": [
        "MEW/USDC:USDC"
    ],
    "MINA": [
        "MINA/USDC:USDC"
    ],
    "MKR": [
        "MKR/USDC:USDC"
    ],
    "MNT": [
        "MNT/USDC:USDC"
    ],
    "MOODENG": [
        "MOODENG/USDC:USDC"
    ],
    "MORPHO": [
        "MORPHO/USDC:USDC"
    ],
    "MOVE": [
        "MOVE/USDC:USDC"
    ],
    "MYRO": [
        "MYRO/USDC:USDC"
    ],
    "NEAR": [
        "NEAR/USDC:USDC"
    ],
    "NEIRO": [
        "KNEIRO/USDC:USDC"
    ],
    "NEIROETH": [
        "NEIROETH/USDC:USDC"
    ],
    "NEO": [
        "NEO/USDC:USDC"
    ],
    "NFTI": [
        "NFTI/USDC:USDC"
    ],
    "NIL": [
        "NIL/USDC:USDC"
    ],
    "NOT": [
        "NOT/USDC:USDC"
    ],
    "NTRN": [
        "NTRN/USDC:USDC"
    ],
    "NXPC": [
        "NXPC/USDC:USDC"
    ],
    "OGN": [
        "OGN/USDC:USDC"
    ],
    "OM": [
        "OM/USDC:USDC"
    ],
    "OMNI": [
        "OMNI/USDC:USDC"
    ],
    "ONDO": [
        "ONDO/USDC:USDC"
    ],
    "OP": [
        "OP/USDC:USDC"
    ],
    "ORBS": [
        "ORBS/USDC:USDC"
    ],
    "ORDI": [
        "ORDI/USDC:USDC"
    ],
    "OX": [
        "OX/USDC:USDC"
    ],
    "PANDORA": [
        "PANDORA/USDC:USDC"
    ],
    "PAXG": [
        "PAXG/USDC:USDC"
    ],
    "PENDLE": [
        "PENDLE/USDC:USDC"
    ],
    "PENGU": [
        "PENGU/USDC:USDC"
    ],
    "PEOPLE": [
        "PEOPLE/USDC:USDC"
    ],
    "PEPE": [
        "KPEPE/USDC:USDC"
    ],
    "PIXEL": [
        "PIXEL/USDC:USDC"
    ],
    "PNUT": [
        "PNUT/USDC:USDC"
    ],
    "POL": [
        "POL/USDC:USDC"
    ],
    "POLYX": [
        "POLYX/USDC:USDC"
    ],
    "POPCAT": [
        "POPCAT/USDC:USDC"
    ],
    "PROMPT": [
        "PROMPT/USDC:USDC"
    ],
    "PROVE": [
        "PROVE/USDC:USDC"
    ],
    "PUMP": [
        "PUMP/USDC:USDC"
    ],
    "PURR": [
        "PURR/USDC:USDC"
    ],
    "PYTH": [
        "PYTH/USDC:USDC"
    ],
    "RDNT": [
        "RDNT/USDC:USDC"
    ],
    "RENDER": [
        "RENDER/USDC:USDC"
    ],
    "REQ": [
        "REQ/USDC:USDC"
    ],
    "RESOLV": [
        "RESOLV/USDC:USDC"
    ],
    "REZ": [
        "REZ/USDC:USDC"
    ],
    "RLB": [
        "RLB/USDC:USDC"
    ],
    "RNDR": [
        "RNDR/USDC:USDC"
    ],
    "RSR": [
        "RSR/USDC:USDC"
    ],
    "RUNE": [
        "RUNE/USDC:USDC"
    ],
    "S": [
        "S/USDC:USDC"
    ],
    "SAGA": [
        "SAGA/USDC:USDC"
    ],
    "SAND": [
        "SAND/USDC:USDC"
    ],
    "SCR": [
        "SCR/USDC:USDC"
    ],
    "SEI": [
        "SEI/USDC:USDC"
    ],
    "SHIA": [
        "SHIA/USDC:USDC"
    ],
    "SHIB": [
        "KSHIB/USDC:USDC"
    ],
    "SNX": [
        "SNX/USDC:USDC"
    ],
    "SOL": [
        "SOL/USDC:USDC"
    ],
    "SOPH": [
        "SOPH/USDC:USDC"
    ],
    "SPX": [
        "SPX/USDC:USDC"
    ],
    "STG": [
        "STG/USDC:USDC"
    ],
    "STRAX": [
        "STRAX/USDC:USDC"
    ],
    "STRK": [
        "STRK/USDC:USDC"
    ],
    "STX": [
        "STX/USDC:USDC"
    ],
    "SUI": [
        "SUI/USDC:USDC"
    ],
    "SUPER": [
        "SUPER/USDC:USDC"
    ],
    "SUSHI": [
        "SUSHI/USDC:USDC"
    ],
    "SYRUP": [
        "SYRUP/USDC:USDC"
    ],
    "TAO": [
        "TAO/USDC:USDC"
    ],
    "TIA": [
        "TIA/USDC:USDC"
    ],
    "TNSR": [
        "TNSR/USDC:USDC"
    ],
    "TON": [
        "TON/USDC:USDC"
    ],
    "TRB": [
        "TRB/USDC:USDC"
    ],
    "TRUMP": [
        "TRUMP/USDC:USDC"
    ],
    "TRX": [
        "TRX/USDC:USDC"
    ],
    "TST": [
        "TST/USDC:USDC"
    ],
    "TURBO": [
        "TURBO/USDC:USDC"
    ],
    "UMA": [
        "UMA/USDC:USDC"
    ],
    "UNI": [
        "UNI/USDC:USDC"
    ],
    "UNIBOT": [
        "UNIBOT/USDC:USDC"
    ],
    "USTC": [
        "USTC/USDC:USDC"
    ],
    "USUAL": [
        "USUAL/USDC:USDC"
    ],
    "VINE": [
        "VINE/USDC:USDC"
    ],
    "VIRTUAL": [
        "VIRTUAL/USDC:USDC"
    ],
    "VVV": [
        "VVV/USDC:USDC"
    ],
    "W": [
        "W/USDC:USDC"
    ],
    "WCT": [
        "WCT/USDC:USDC"
    ],
    "WIF": [
        "WIF/USDC:USDC"
    ],
    "WLD": [
        "WLD/USDC:USDC"
    ],
    "WLFI": [
        "WLFI/USDC:USDC"
    ],
    "XAI": [
        "XAI/USDC:USDC"
    ],
    "XLM": [
        "XLM/USDC:USDC"
    ],
    "XPL": [
        "XPL/USDC:USDC"
    ],
    "XRP": [
        "XRP/USDC:USDC"
    ],
    "YGG": [
        "YGG/USDC:USDC"
    ],
    "YZY": [
        "YZY/USDC:USDC"
    ],
    "ZEN": [
        "ZEN/USDC:USDC"
    ],
    "ZEREBRO": [
        "ZEREBRO/USDC:USDC"
    ],
    "ZETA": [
        "ZETA/USDC:USDC"
    ],
    "ZK": [
        "ZK/USDC:USDC"
    ],
    "ZORA": [
        "ZORA/USDC:USDC"
    ],
    "ZRO": [
        "ZRO/USDC:USDC"
    ],
    "kBONK": [
        "KBONK/USDC:USDC"
    ],
    "kDOGS": [
        "KDOGS/USDC:USDC"
    ],
    "kFLOKI": [
        "KFLOKI/USDC:USDC"
    ],
    "kLUNC": [
        "KLUNC/USDC:USDC"
    ],
    "kNEIRO": [
        "KNEIRO/USDC:USDC"
    ],
    "kPEPE": [
        "KPEPE/USDC:USDC"
    ],
    "kSHIB": [
        "KSHIB/USDC:USDC"
    ]
}